MSK07/MSK07.py
MSK07/__init__.py
MSK07-0.7.dist-info/LICENSE.txt
MSK07-0.7.dist-info/METADATA
MSK07-0.7.dist-info/WHEEL
MSK07-0.7.dist-info/top_level.txt
MSK07-0.7.dist-info/RECORD
