Metadata-Version: 2.1
Name: MSK07
Version: 0.7
Summary: Pacote teste do Massaki
Home-page: https://github.com/massakiigarashi2/
Author: Seu Nome
Author-email: prof.massaki@gmail.com
Classifier: Programming Language :: Python :: 3
Classifier: License :: OSI Approved :: MIT License
Classifier: Operating System :: OS Independent
Requires-Python: >=3.10
License-File: LICENSE.txt
Requires-Dist: pandas
Requires-Dist: numpy
